flask_template_cli/__init__.py
flask_template_cli/cli.py
flask_template_cli/test.py
flask_template_cli/types.py
flask_template_cli/templates/__init__.py
flask_template_cli/templates/auth_gen.py
flask_template_cli/templates/init_gen.py
flask_template_cli/templates/models_gen.py
flask_template_cli/templates/req_txt_gen.py
flask_template_cli/templates/routes_gen.py
flask_template_cli-0.2.0.dist-info/METADATA
flask_template_cli-0.2.0.dist-info/WHEEL
flask_template_cli-0.2.0.dist-info/entry_points.txt
flask_template_cli-0.2.0.dist-info/top_level.txt
flask_template_cli-0.2.0.dist-info/RECORD
