Metadata-Version: 2.1
Name: flask_template_cli
Version: 0.2.0
Summary: Description of my package
Home-page: https://github.com/saipraveenkondapalli/flask_template_cli
Author: Sai Praveen Kondapalli
Author-email: saipraveenkondapalli@gmail.com
Requires-Dist: typer
Requires-Dist: rich
Requires-Dist: InquirerPy
